localleaf/__init__.py
localleaf/__main__.py
localleaf/browser.py
localleaf/cli.py
localleaf/client.py
localleaf/settings.py
localleaf-1.1.2.dist-info/entry_points.txt
localleaf-1.1.2.dist-info/licenses/LICENSE
localleaf-1.1.2.dist-info/WHEEL
localleaf-1.1.2.dist-info/METADATA
localleaf-1.1.2.dist-info/RECORD
