Metadata-Version: 2.4
Name: localleaf
Version: 1.1.2
Summary: Manage your Overleaf projects locally
Keywords: overleaf,local,sync,latex,tex
Author-email: Jaziel Loureiro <jazielloureiro17@gmail.com>, Moritz Glöckl <moritzgloeckl@users.noreply.github.com>
Maintainer-email: Jaziel Loureiro <jazielloureiro17@gmail.com>
Requires-Python: >=3
Classifier: License :: OSI Approved :: MIT License
Classifier: Intended Audience :: Science/Research
Classifier: Programming Language :: Python :: 3
License-File: LICENSE
Requires-Dist: beautifulsoup4==4.13.4
Requires-Dist: certifi==2025.4.26
Requires-Dist: charset-normalizer==3.4.2
Requires-Dist: click==8.2.0
Requires-Dist: colorama==0.4.6
Requires-Dist: idna==3.10
Requires-Dist: platformdirs==4.3.8
Requires-Dist: pyside6==6.9.0
Requires-Dist: pyside6-addons==6.9.0
Requires-Dist: pyside6-essentials==6.9.0
Requires-Dist: python-dateutil==2.9.0.post0
Requires-Dist: requests==2.32.3
Requires-Dist: shiboken6==6.9.0
Requires-Dist: six==1.17.0
Requires-Dist: soupsieve==2.7
Requires-Dist: typing-extensions==4.13.2
Requires-Dist: urllib3==2.4.0
Requires-Dist: websocket-client==1.8.0
Project-URL: Source, https://github.com/jazielloureiro/LocalLeaf
